{
  "410662767981232128": {
    "userId": "410662767981232128",
    "username": "mr.z6931",
    "points": 740,
    "activeWallet": 1,
    "wallets": [
      {
        "walletId": 1,
        "inventory": {
          "lootBoxes": 52,
          "airdropAllocations": 0,
          "sparkTokens": 0
        },
        "sparkWalletAddress": "123",
        "taprootWalletAddress": "123"
      }
    ],
    "inviteData": {
      "inviteCode": "",
      "uses": 0,
      "pointsEarned": 0,
      "invitedUsers": []
    },
    "reactionData": {},
    "gmCooldown": 0,
    "twitterHandle": "username",
    "lastLootBoxOpen": 1761235277345
  }
}